creditprice/__init__.py
creditprice/creditprice.py
creditprice-0.0.8.dist-info/LICENCE
creditprice-0.0.8.dist-info/METADATA
creditprice-0.0.8.dist-info/WHEEL
creditprice-0.0.8.dist-info/top_level.txt
creditprice-0.0.8.dist-info/RECORD
