Metadata-Version: 2.1
Name: creditprice
Version: 0.0.8
Summary: Credit price tool
Home-page: https://github.com/pypa/sampleproject
Author: Fei Wu
Author-email: wufei.pku@163.com
License: UNKNOWN
Platform: UNKNOWN
Classifier: Programming Language :: Python :: 3
Classifier: License :: OSI Approved :: MIT License
Classifier: Operating System :: OS Independent
Requires-Dist: pandas (>=0.24.0)
Requires-Dist: numpy (>=1.16.0)
Requires-Dist: scipy (>=1.4.1)
Requires-Dist: joblib (>=0.14.0)
Requires-Dist: matplotlib
